ua_eds_api/__init__.py
ua_eds_api/grouper_to_redmine.py
ua_eds_api/ua_eds_api.py
ua_eds_api-1.0.1.dist-info/LICENSE
ua_eds_api-1.0.1.dist-info/METADATA
ua_eds_api-1.0.1.dist-info/WHEEL
ua_eds_api-1.0.1.dist-info/top_level.txt
ua_eds_api-1.0.1.dist-info/RECORD
