Metadata-Version: 2.1
Name: ua-eds-api
Version: 1.0.1
Summary: Provides easy interface for making REST requests to University of Arizona EDS registry.
Home-page: https://github.com/UACoreFacilitiesIT/UA-EDS-API
Author: Ryan Johannes-Bland
Author-email: rjjohannesbland@email.arizona.edu
License: MIT
Platform: UNKNOWN
Requires-Dist: requests
Requires-Dist: bs4
